fsrs_optimizer/__init__.py
fsrs_optimizer/__main__.py
fsrs_optimizer/fsrs_optimizer.py
fsrs_optimizer/fsrs_simulator.py
fsrs_optimizer-6.4.0.dist-info/LICENSE
fsrs_optimizer-6.4.0.dist-info/METADATA
fsrs_optimizer-6.4.0.dist-info/WHEEL
fsrs_optimizer-6.4.0.dist-info/top_level.txt
fsrs_optimizer-6.4.0.dist-info/RECORD
