Metadata-Version: 2.1
Name: FSRS-Optimizer
Version: 6.4.0
Project-URL: Homepage, https://github.com/open-spaced-repetition/fsrs-optimizer
Requires-Python: <3.14,>=3.10
License-File: LICENSE
Requires-Dist: matplotlib
Requires-Dist: numpy
Requires-Dist: pandas
Requires-Dist: pytz
Requires-Dist: scikit-learn
Requires-Dist: torch
Requires-Dist: tqdm
Requires-Dist: statsmodels
Requires-Dist: scipy
Provides-Extra: test
Requires-Dist: ruff; extra == "test"
Requires-Dist: pyrefly; extra == "test"
Requires-Dist: pytest; extra == "test"
Requires-Dist: pytest-cov; extra == "test"
